xltojson/__init__.py
xltojson/parse.py
xltojson-1.1.2.dist-info/LICENSE
xltojson-1.1.2.dist-info/METADATA
xltojson-1.1.2.dist-info/WHEEL
xltojson-1.1.2.dist-info/top_level.txt
xltojson-1.1.2.dist-info/RECORD
